mt_scraper/__init__.py
mt_scraper/dummy_parser.py
mt_scraper/mt_scraper.py
mt_scraper-0.4.0.dist-info/METADATA
mt_scraper-0.4.0.dist-info/WHEEL
mt_scraper-0.4.0.dist-info/top_level.txt
mt_scraper-0.4.0.dist-info/RECORD
