Metadata-Version: 2.1
Name: mt-scraper
Version: 0.4.0
Summary: Easy multythread web scraper
Home-page: https://bitbucket.org/dronych/mt_scraper-project
Author: Andrey Sechenov
Author-email: dronych@mail.ru
License: UNKNOWN
Platform: UNKNOWN
Classifier: Programming Language :: Python :: 3
Classifier: License :: OSI Approved :: MIT License
Classifier: Operating System :: OS Independent
Requires-Dist: PySocks (==1.7.0)
